aiomono/__init__.py
aiomono/client.py
aiomono/exceptions.py
aiomono/types.py
aiomono/utils.py
aiomono-1.1.8.dist-info/METADATA
aiomono-1.1.8.dist-info/WHEEL
aiomono-1.1.8.dist-info/top_level.txt
aiomono-1.1.8.dist-info/RECORD
