Metadata-Version: 2.4
Name: aiomono
Version: 1.1.8
Summary: Add your description here
Requires-Python: >=3.12
Requires-Dist: httpx>=0.28.1
Requires-Dist: pydantic>=2.11.7
